{
	"name": "Giga Impact",
	"note": "",
	"type":" Normal ",
	"category": "Physical",
	"pp": "5",
	"power": "150",
	"accuracy": "90",
	"summary": "Deals damage, and the user has to charge on the next turn, making it not attack. This charge turn can be bypassed with Power Herb.",
	"viability": "These charging moves, like Hyper Beam, are generally terrible because of the charge turn. Even with Power Herb, you can really only use it once. In reality, with the two turns, you're only having a 70 BP move on average.",
	"pokemonByLevel": [
		{ "pokemonName": "Tauros" },
		{ "pokemonName": "Aerodactyl" },
		{ "pokemonName": "Snorlax" },
		{ "pokemonName": "Donphan" },
		{ "pokemonName": "Tyranitar" },
		{ "pokemonName": "Electivire" },
		{ "pokemonName": "Regigigas" },
		{ "pokemonName": "Lillipup" },
		{ "pokemonName": "Herdier" },
		{ "pokemonName": "Stoutland" },
		{ "pokemonName": "Escavalier" },
		{ "pokemonName": "Axew" },
		{ "pokemonName": "Fraxure" },
		{ "pokemonName": "Haorus" },
		{ "pokemonName": "Bouffalant" },
		{ "pokemonName": "Chesnaught" },
		{ "pokemonName": "Tyrantrum" },
		{ "pokemonName": "Xerneas" }
	],
	"pokemonByBreeding": [
	],
	"pokemonByTM": [
	{"pokemonName": "Venusaur"},
{"pokemonName": "Charizard"},
{"pokemonName": "Blastoise"},
{"pokemonName": "Butterfree"},
{"pokemonName": "Beedrill"},
{"pokemonName": "Pidgeot"},
{"pokemonName": "Raticate"},
{"pokemonName": "Fearow"},
{"pokemonName": "Arbok"},
{"pokemonName": "Raichu"},
{"pokemonName": "Sandslash"},
{"pokemonName": "Nidoqueen"},
{"pokemonName": "Nidoking"},
{"pokemonName": "Clefable"},
{"pokemonName": "Ninetales"},
{"pokemonName": "Wigglytuff"},
{"pokemonName": "Golbat"},
{"pokemonName": "Vileplume"},
{"pokemonName": "Parasect"},
{"pokemonName": "Venomoth"},
{"pokemonName": "Dugtrio"},
{"pokemonName": "Persian"},
{"pokemonName": "Golduck"},
{"pokemonName": "Primeape"},
{"pokemonName": "Arcanine"},
{"pokemonName": "Poliwrath"},
{"pokemonName": "Alakazam"},
{"pokemonName": "Machamp"},
{"pokemonName": "Victreebel"},
{"pokemonName": "Tentacruel"},
{"pokemonName": "Golem"},
{"pokemonName": "Rapidash"},
{"pokemonName": "Slowbro"},
{"pokemonName": "Magneton"},
{"pokemonName": "Dodrio"},
{"pokemonName": "Dewgong"},
{"pokemonName": "Muk"},
{"pokemonName": "Cloyster"},
{"pokemonName": "Gengar"},
{"pokemonName": "Hypno"},
{"pokemonName": "Kingler"},
{"pokemonName": "Electrode"},
{"pokemonName": "Exeggutor"},
{"pokemonName": "Marowak"},
{"pokemonName": "Lickitung"},
{"pokemonName": "Weezing"},
{"pokemonName": "Rhydon"},
{"pokemonName": "Chansey"},
{"pokemonName": "Tangela"},
{"pokemonName": "Kangaskhan"},
{"pokemonName": "Seadra"},
{"pokemonName": "Seaking"},
{"pokemonName": "Starmie"},
{"pokemonName": "Mr. Mime"},
{"pokemonName": "Scyther"},
{"pokemonName": "Jynx"},
{"pokemonName": "Electabuzz"},
{"pokemonName": "Magmar"},
{"pokemonName": "Pinsir"},
{"pokemonName": "Tauros"},
{"pokemonName": "Gyarados"},
{"pokemonName": "Lapras"},
{"pokemonName": "Vaporeon"},
{"pokemonName": "Jolteon"},
{"pokemonName": "Flareon"},
{"pokemonName": "Porygon"},
{"pokemonName": "Omastar"},
{"pokemonName": "Kabutops"},
{"pokemonName": "Aerodactyl"},
{"pokemonName": "Snorlax"},
{"pokemonName": "Articuno"},
{"pokemonName": "Zapdos"},
{"pokemonName": "Moltres"},
{"pokemonName": "Dragonite"},
{"pokemonName": "Mewtwo"},
{"pokemonName": "Mew"},
{"pokemonName": "Meganium"},
{"pokemonName": "Typhlosion"},
{"pokemonName": "Feraligatr"},
{"pokemonName": "Furret"},
{"pokemonName": "Noctowl"},
{"pokemonName": "Ledian"},
{"pokemonName": "Ariados"},
{"pokemonName": "Crobat"},
{"pokemonName": "Lanturn"},
{"pokemonName": "Togetic"},
{"pokemonName": "Xatu"},
{"pokemonName": "Ampharos"},
{"pokemonName": "Bellossom"},
{"pokemonName": "Azumarill"},
{"pokemonName": "Politoed"},
{"pokemonName": "Jumpluff"},
{"pokemonName": "Sunflora"},
{"pokemonName": "Quagsire"},
{"pokemonName": "Espeon"},
{"pokemonName": "Umbreon"},
{"pokemonName": "Slowking"},
{"pokemonName": "Forretress"},
{"pokemonName": "Steelix"},
{"pokemonName": "Granbull"},
{"pokemonName": "Scizor"},
{"pokemonName": "Heracross"},
{"pokemonName": "Ursaring"},
{"pokemonName": "Magcargo"},
{"pokemonName": "Piloswine"},
{"pokemonName": "Octillery"},
{"pokemonName": "Mantine"},
{"pokemonName": "Houndoom"},
{"pokemonName": "Kingdra"},
{"pokemonName": "Donphan"},
{"pokemonName": "Porygon2"},
{"pokemonName": "Stantler"},
{"pokemonName": "Miltank"},
{"pokemonName": "Blissey"},
{"pokemonName": "Raikou"},
{"pokemonName": "Entei"},
{"pokemonName": "Suicune"},
{"pokemonName": "Tyranitar"},
{"pokemonName": "Lugia"},
{"pokemonName": "Ho-Oh"},
{"pokemonName": "Celebi"},
{"pokemonName": "Sceptile"},
{"pokemonName": "Blaziken"},
{"pokemonName": "Swampert"},
{"pokemonName": "Mightyena"},
{"pokemonName": "Linoone"},
{"pokemonName": "Beautifly"},
{"pokemonName": "Dustox"},
{"pokemonName": "Ludicolo"},
{"pokemonName": "Shiftry"},
{"pokemonName": "Swellow"},
{"pokemonName": "Pelipper"},
{"pokemonName": "Gardevoir"},
{"pokemonName": "Masquerain"},
{"pokemonName": "Breloom"},
{"pokemonName": "Slaking"},
{"pokemonName": "Ninjask"},
{"pokemonName": "Shedinja"},
{"pokemonName": "Exploud"},
{"pokemonName": "Hariyama"},
{"pokemonName": "Delcatty"},
{"pokemonName": "Mawile"},
{"pokemonName": "Aggron"},
{"pokemonName": "Medicham"},
{"pokemonName": "Manectric"},
{"pokemonName": "Swalot"},
{"pokemonName": "Sharpedo"},
{"pokemonName": "Wailord"},
{"pokemonName": "Camerupt"},
{"pokemonName": "Torkoal"},
{"pokemonName": "Grumpig"},
{"pokemonName": "Flygon"},
{"pokemonName": "Cacturne"},
{"pokemonName": "Altaria"},
{"pokemonName": "Lunatone"},
{"pokemonName": "Solrock"},
{"pokemonName": "Whiscash"},
{"pokemonName": "Crawdaunt"},
{"pokemonName": "Claydol"},
{"pokemonName": "Cradily"},
{"pokemonName": "Armaldo"},
{"pokemonName": "Milotic"},
{"pokemonName": "Banette"},
{"pokemonName": "Dusclops"},
{"pokemonName": "Tropius"},
{"pokemonName": "Absol"},
{"pokemonName": "Glalie"},
{"pokemonName": "Walrein"},
{"pokemonName": "Huntail"},
{"pokemonName": "Gorebyss"},
{"pokemonName": "Relicanth"},
{"pokemonName": "Salamence"},
{"pokemonName": "Metagross"},
{"pokemonName": "Regirock"},
{"pokemonName": "Regice"},
{"pokemonName": "Registeel"},
{"pokemonName": "Latias"},
{"pokemonName": "Latios"},
{"pokemonName": "Kyogre"},
{"pokemonName": "Groudon"},
{"pokemonName": "Rayquaza"},
{"pokemonName": "Jirachi"},
{"pokemonName": "Deoxys"},
{"pokemonName": "Torterra"},
{"pokemonName": "Infernape"},
{"pokemonName": "Empoleon"},
{"pokemonName": "Staraptor"},
{"pokemonName": "Bibarel"},
{"pokemonName": "Kricketune"},
{"pokemonName": "Luxray"},
{"pokemonName": "Roserade"},
{"pokemonName": "Rampardos"},
{"pokemonName": "Bastiodon"},
{"pokemonName": "Wormadam"},
{"pokemonName": "Mothim"},
{"pokemonName": "Vespiquen"},
{"pokemonName": "Floatzel"},
{"pokemonName": "Cherrim"},
{"pokemonName": "Gastrodon"},
{"pokemonName": "Ambipom"},
{"pokemonName": "Drifblim"},
{"pokemonName": "Lopunny"},
{"pokemonName": "Mismagius"},
{"pokemonName": "Honchkrow"},
{"pokemonName": "Purugly"},
{"pokemonName": "Skuntank"},
{"pokemonName": "Bronzong"},
{"pokemonName": "Spiritomb"},
{"pokemonName": "Garchomp"},
{"pokemonName": "Lucario"},
{"pokemonName": "Hippowdon"},
{"pokemonName": "Drapion"},
{"pokemonName": "Toxicroak"},
{"pokemonName": "Carnivine"},
{"pokemonName": "Lumineon"},
{"pokemonName": "Abomasnow"},
{"pokemonName": "Weavile"},
{"pokemonName": "Magnezone"},
{"pokemonName": "Lickilicky"},
{"pokemonName": "Rhyperior"},
{"pokemonName": "Tangrowth"},
{"pokemonName": "Electivire"},
{"pokemonName": "Magmortar"},
{"pokemonName": "Togekiss"},
{"pokemonName": "Yanmega"},
{"pokemonName": "Leafeon"},
{"pokemonName": "Glaceon"},
{"pokemonName": "Gliscor"},
{"pokemonName": "Mamoswine"},
{"pokemonName": "Porygon-Z"},
{"pokemonName": "Gallade"},
{"pokemonName": "Probopass"},
{"pokemonName": "Dusknoir"},
{"pokemonName": "Froslass"},
{"pokemonName": "Uxie"},
{"pokemonName": "Mesprit"},
{"pokemonName": "Azelf"},
{"pokemonName": "Dialga"},
{"pokemonName": "Palkia"},
{"pokemonName": "Heatran"},
{"pokemonName": "Regigigas"},
{"pokemonName": "Giratina"},
{"pokemonName": "Cresselia"},
{"pokemonName": "Manaphy"},
{"pokemonName": "Darkrai"},
{"pokemonName": "Shaymin"},
{"pokemonName": "Arceus"},
{"pokemonName": "Victini"},
{"pokemonName": "Serperior"},
{"pokemonName": "Emboar"},
{"pokemonName": "Samurott"},
{"pokemonName": "Watchog"},
{"pokemonName": "Lillipup"},
{"pokemonName": "Herdier"},
{"pokemonName": "Stoutland"},
{"pokemonName": "Liepard"},
{"pokemonName": "Simisage"},
{"pokemonName": "Simisear"},
{"pokemonName": "Simipour"},
{"pokemonName": "Musharna"},
{"pokemonName": "Unfezant"},
{"pokemonName": "Zebstrika"},
{"pokemonName": "Gigalith"},
{"pokemonName": "Swoobat"},
{"pokemonName": "Excadrill"},
{"pokemonName": "Conkeldurr"},
{"pokemonName": "Seismitoad"},
{"pokemonName": "Throh"},
{"pokemonName": "Sawk"},
{"pokemonName": "Leavanny"},
{"pokemonName": "Scolipede"},
{"pokemonName": "Whimsicott"},
{"pokemonName": "Lilligant"},
{"pokemonName": "Krookodile"},
{"pokemonName": "Darmanitan"},
{"pokemonName": "Crustle"},
{"pokemonName": "Scrafty"},
{"pokemonName": "Cofagrigus"},
{"pokemonName": "Carracosta"},
{"pokemonName": "Archeops"},
{"pokemonName": "Garbodor"},
{"pokemonName": "Zoroark"},
{"pokemonName": "Cinccino"},
{"pokemonName": "Gothitelle"},
{"pokemonName": "Reuniclus"},
{"pokemonName": "Swanna"},
{"pokemonName": "Vanilluxe"},
{"pokemonName": "Sawsbuck"},
{"pokemonName": "Escavalier"},
{"pokemonName": "Amoonguss"},
{"pokemonName": "Jellicent"},
{"pokemonName": "Galvantula"},
{"pokemonName": "Ferrothorn"},
{"pokemonName": "Klink"},
{"pokemonName": "Klang"},
{"pokemonName": "Klinklang"},
{"pokemonName": "Eelektross"},
{"pokemonName": "Beheeyem"},
{"pokemonName": "Chandelure"},
{"pokemonName": "Axew"},
{"pokemonName": "Fraxure"},
{"pokemonName": "Haxorus"},
{"pokemonName": "Beartic"},
{"pokemonName": "Accelgor"},
{"pokemonName": "Mienshao"},
{"pokemonName": "Druddigon"},
{"pokemonName": "Golurk"},
{"pokemonName": "Bisharp"},
{"pokemonName": "Bouffalant"},
{"pokemonName": "Braviary"},
{"pokemonName": "Mandibuzz"},
{"pokemonName": "Heatmor"},
{"pokemonName": "Durant"},
{"pokemonName": "Hydreigon"},
{"pokemonName": "Volcarona"},
{"pokemonName": "Cobalion"},
{"pokemonName": "Terrakion"},
{"pokemonName": "Virizion"},
{"pokemonName": "Tornadus-Incarnate"},
{"pokemonName": "Tornadus-Therian"},
{"pokemonName": "Thundurus-Incarnate"},
{"pokemonName": "Thundurus-Therian"},
{"pokemonName": "Reshiram"},
{"pokemonName": "Zekrom"},
{"pokemonName": "Landorus-Incarnate"},
{"pokemonName": "Landorus-Therian"},
{"pokemonName": "Kyurem"},
{"pokemonName": "Keldeo"},
{"pokemonName": "Meloetta-Aria"},
{"pokemonName": "Meloetta-Pirouette"},
{"pokemonName": "Genesect"},
{"pokemonName": "Chesnaught"},
{"pokemonName": "Delphox"},
{"pokemonName": "Greninja"},
{"pokemonName": "Diggersby"},
{"pokemonName": "Talonflame"},
{"pokemonName": "Vivillon"},
{"pokemonName": "Pyroar"},
{"pokemonName": "Florges"},
{"pokemonName": "Gogoat"},
{"pokemonName": "Pangoro"},
{"pokemonName": "Furfrou"},
{"pokemonName": "Meowstic"},
{"pokemonName": "Aegislash"},
{"pokemonName": "Aromatisse"},
{"pokemonName": "Slurpuff"},
{"pokemonName": "Malamar"},
{"pokemonName": "Barbaracle"},
{"pokemonName": "Dragalge"},
{"pokemonName": "Clawitzer"},
{"pokemonName": "Heliolisk"},
{"pokemonName": "Tyrantrum"},
{"pokemonName": "Aurorus"},
{"pokemonName": "Sylveon"},
{"pokemonName": "Hawlucha"},
{"pokemonName": "Dedenne"},
{"pokemonName": "Goodra"},
{"pokemonName": "Klefki"},
{"pokemonName": "Trevenant"},
{"pokemonName": "Gourgeist-Small"},
{"pokemonName": "Gourgeist-Average"},
{"pokemonName": "Gourgeist-Large"},
{"pokemonName": "Gourgeist-Super"},
{"pokemonName": "Avalugg"},
{"pokemonName": "Noivern"},
{"pokemonName": "Xerneas"},
{"pokemonName": "Yveltal"},
{"pokemonName": "Zygarde"},
{"pokemonName": "Diancie"},
{"pokemonName": "Hoopa"},
{"pokemonName": "Hoopa-Unbound"},
{"pokemonName": "Volcanion"}
	],
	"pokemonByHM": [
	],
	"pokemonByTutor": [
	]
}
