{
	"name": "Incinerate",
	"note": "",
	"type":" Fire ",
	"category": "Special",
	"pp": "15",
	"power": "60",
	"accuracy": "100",
	"summary": "Deals damage and destroys the target's Berry. The Occa Berry will be used before this move is executed. Also makes Gems unusable",
	"viability": "Incinerate, while not powerful, can be useful in a format where berries are common. It can even stop some Harvest Pokemon like Exeggutor from stalling.",
	"pokemonByLevel": [
		{ "pokemonName": "Slugma" },
		{ "pokemonName": "Magcargo" },
		{ "pokemonName": "Victini" },
		{ "pokemonName": "Pansear" },
		{ "pokemonName": "Darumaka" },
		{ "pokemonName": "Darmanitan" },
		{ "pokemonName": "Heatmor" },
		{ "pokemonName": "Litleo" },
		{ "pokemonName": "Male Pyroar" },
		{ "pokemonName": "Female Pyroar" }
	],
	"pokemonByBreeding": [
	],
	"pokemonByTM": [
	{"pokemonName": "Charmander" },
{"pokemonName": "Charmeleon" },
{"pokemonName": "Charizard" },
{"pokemonName": "Nidoqueen" },
{"pokemonName": "Nidoking" },
{"pokemonName": "Clefairy" },
{"pokemonName": "Clefable" },
{"pokemonName": "Vulpix" },
{"pokemonName": "Ninetales" },
{"pokemonName": "Jigglypuff" },
{"pokemonName": "Wigglytuff" },
{"pokemonName": "Growlithe" },
{"pokemonName": "Arcanine" },
{"pokemonName": "Machop" },
{"pokemonName": "Machoke" },
{"pokemonName": "Machamp" },
{"pokemonName": "Geodude" },
{"pokemonName": "Graveler" },
{"pokemonName": "Golem" },
{"pokemonName": "Ponyta" },
{"pokemonName": "Rapidash" },
{"pokemonName": "Slowpoke" },
{"pokemonName": "Slowbro" },
{"pokemonName": "Grimer" },
{"pokemonName": "Muk" },
{"pokemonName": "Cubone" },
{"pokemonName": "Marowak" },
{"pokemonName": "Lickitung" },
{"pokemonName": "Koffing" },
{"pokemonName": "Weezing" },
{"pokemonName": "Rhyhorn" },
{"pokemonName": "Rhydon" },
{"pokemonName": "Chansey" },
{"pokemonName": "Kangaskhan" },
{"pokemonName": "Magmar" },
{"pokemonName": "Tauros" },
{"pokemonName": "Gyarados" },
{"pokemonName": "Flareon" },
{"pokemonName": "Aerodactyl" },
{"pokemonName": "Snorlax" },
{"pokemonName": "Moltres" },
{"pokemonName": "Dratini" },
{"pokemonName": "Dragonair" },
{"pokemonName": "Dragonite" },
{"pokemonName": "Mewtwo" },
{"pokemonName": "Mew" },
{"pokemonName": "Cyndaquil" },
{"pokemonName": "Quilava" },
{"pokemonName": "Typhlosion" },
{"pokemonName": "Cleffa" },
{"pokemonName": "Igglybuff" },
{"pokemonName": "Togepi" },
{"pokemonName": "Togetic" },
{"pokemonName": "Slowking" },
{"pokemonName": "Dunsparce" },
{"pokemonName": "Snubbull" },
{"pokemonName": "Granbull" },
{"pokemonName": "Slugma" },
{"pokemonName": "Magcargo" },
{"pokemonName": "Remoraid" },
{"pokemonName": "Octillery" },
{"pokemonName": "Houndour" },
{"pokemonName": "Houndoom" },
{"pokemonName": "Magby" },
{"pokemonName": "Blissey" },
{"pokemonName": "Entei" },
{"pokemonName": "Tyranitar" },
{"pokemonName": "Ho-Oh" },
{"pokemonName": "Torchic" },
{"pokemonName": "Combusken" },
{"pokemonName": "Blaziken" },
{"pokemonName": "Poochyena" },
{"pokemonName": "Mightyena" },
{"pokemonName": "Slakoth" },
{"pokemonName": "Vigoroth" },
{"pokemonName": "Slaking" },
{"pokemonName": "Whismur" },
{"pokemonName": "Loudred" },
{"pokemonName": "Exploud" },
{"pokemonName": "Sableye" },
{"pokemonName": "Mawile" },
{"pokemonName": "Aggron" },
{"pokemonName": "Numel" },
{"pokemonName": "Camerupt" },
{"pokemonName": "Torkoal" },
{"pokemonName": "Flygon" },
{"pokemonName": "Altaria" },
{"pokemonName": "Zangoose" },
{"pokemonName": "Solrock" },
{"pokemonName": "Castform" },
{"pokemonName": "Kecleon" },
{"pokemonName": "Absol" },
{"pokemonName": "Bagon" },
{"pokemonName": "Shelgon" },
{"pokemonName": "Salamence" },
{"pokemonName": "Groudon" },
{"pokemonName": "Rayquaza" },
{"pokemonName": "Chimchar" },
{"pokemonName": "Monferno" },
{"pokemonName": "Infernape" },
{"pokemonName": "Cranidos" },
{"pokemonName": "Rampardos" },
{"pokemonName": "Shieldon" },
{"pokemonName": "Bastiodon" },
{"pokemonName": "Honchkrow" },
{"pokemonName": "Stunky" },
{"pokemonName": "Skuntank" },
{"pokemonName": "Happiny" },
{"pokemonName": "Gible" },
{"pokemonName": "Gabite" },
{"pokemonName": "Garchomp" },
{"pokemonName": "Munchlax" },
{"pokemonName": "Lickilicky" },
{"pokemonName": "Rhyperior" },
{"pokemonName": "Magmortar" },
{"pokemonName": "Togekiss" },
{"pokemonName": "Azelf" },
{"pokemonName": "Dialga" },
{"pokemonName": "Palkia" },
{"pokemonName": "Heatran" },
{"pokemonName": "Darkrai" },
{"pokemonName": "Arceus" },
{"pokemonName": "Victini" },
{"pokemonName": "Tepig" },
{"pokemonName": "Pignite" },
{"pokemonName": "Emboar" },
{"pokemonName": "Pansear" },
{"pokemonName": "Simisear" },
{"pokemonName": "Audino" },
{"pokemonName": "Sandile" },
{"pokemonName": "Krokorok" },
{"pokemonName": "Krookodile" },
{"pokemonName": "Darumaka" },
{"pokemonName": "Darmanitan" },
{"pokemonName": "Scraggy" },
{"pokemonName": "Scrafty" },
{"pokemonName": "Zorua" },
{"pokemonName": "Zoroark" },
{"pokemonName": "Litwick" },
{"pokemonName": "Lampent" },
{"pokemonName": "Chandelure" },
{"pokemonName": "Axew" },
{"pokemonName": "Fraxure" },
{"pokemonName": "Haxorus" },
{"pokemonName": "Druddigon" },
{"pokemonName": "Vullaby" },
{"pokemonName": "Mandibuzz" },
{"pokemonName": "Heatmor" },
{"pokemonName": "Deino" },
{"pokemonName": "Zweilous" },
{"pokemonName": "Hydreigon" },
{"pokemonName": "Larvesta" },
{"pokemonName": "Volcarona" },
{"pokemonName": "Tornadus-Incarnate" },
{"pokemonName": "Tornadus-Therian" },
{"pokemonName": "Thundurus-Incarnate" },
{"pokemonName": "Thundurus-Therian" },
{"pokemonName": "Reshiram" },
{"pokemonName": "Fennekin" },
{"pokemonName": "Braixen" },
{"pokemonName": "Delphox" },
{"pokemonName": "Fletchinder" },
{"pokemonName": "Talonflame" },
{"pokemonName": "Litleo" },
{"pokemonName": "Male Pyroar" },
{"pokemonName": "Female Pyroar" },
{"pokemonName": "Goodra" },
{"pokemonName": "Pumpkaboo-Small" },
{"pokemonName": "Pumpkaboo-Average" },
{"pokemonName": "Pumpkaboo-Large" },
{"pokemonName": "Pumpkaboo-Super" },
{"pokemonName": "Gourgeist-Small" },
{"pokemonName": "Gourgeist-Average" },
{"pokemonName": "Gourgeist-Large" },
{"pokemonName": "Gourgeist-Super" },
{"pokemonName": "Volcanion" }
	],
	"pokemonByHM": [
	],
	"pokemonByTutor": [
	]
}
