{
	"name": "Magic Coat",
	"note": "",
	"type":" Psychic ",
	"category": "Status",
	"pp": "15",
	"power": "--",
	"accuracy": "--",
	"summary": "Bounces back any status conditions as well as entry hazards. Teeter Dance and Memento are not affected.",
	"viability": "Magic Coat is a great way to trick your opponent that leads with entry hazard support. While it takes a fair amount of predicting, it works quite well.",
	"pokemonByLevel": [
		{ "pokemonName": "Porygon" },
		{ "pokemonName": "Porygon2" },
		{ "pokemonName": "Spoink" },
		{ "pokemonName": "Grumpig" },
		{ "pokemonName": "Lopunny" },
		{ "pokemonName": "Porygon-Z" },
		{ "pokemonName": "Hoopa" },
		{ "pokemonName": "Hoopa-Unbound" },
		{ "pokemonName": "Girafarig" },
		{ "pokemonName": "Dunsparce" },
		{ "pokemonName": "Kecleon" },
		{ "pokemonName": "Absol" },
		{ "pokemonName": "Munna" },
		{ "pokemonName": "Fennekin" }
	],
	"pokemonByBreeding": [
	],
	"pokemonByTM": [
	],
	"pokemonByHM": [
	],
	"pokemonByTutor": [
	{"pokemonName": "lefairy " },
{"pokemonName": "Clefable " },
{"pokemonName": "Jigglypuff " },
{"pokemonName": "Wigglytuff " },
{"pokemonName": "Abra " },
{"pokemonName": "Kadabra " },
{"pokemonName": "Alakazam " },
{"pokemonName": "Tentacool " },
{"pokemonName": "Tentacruel " },
{"pokemonName": "Slowpoke " },
{"pokemonName": "Slowbro " },
{"pokemonName": "Magnemite " },
{"pokemonName": "Magneton " },
{"pokemonName": "Drowzee " },
{"pokemonName": "Hypno " },
{"pokemonName": "Voltorb " },
{"pokemonName": "Electrode " },
{"pokemonName": "Staryu " },
{"pokemonName": "Starmie " },
{"pokemonName": "Mr. Mime" },
{"pokemonName": "Jynx " },
{"pokemonName": "Porygon " },
{"pokemonName": "Mewtwo " },
{"pokemonName": "Mew " },
{"pokemonName": "Chikorita " },
{"pokemonName": "Bayleef " },
{"pokemonName": "Meganium " },
{"pokemonName": "Hoothoot " },
{"pokemonName": "Noctowl " },
{"pokemonName": "Cleffa " },
{"pokemonName": "Igglybuff " },
{"pokemonName": "Togepi " },
{"pokemonName": "Togetic " },
{"pokemonName": "Natu " },
{"pokemonName": "Xatu " },
{"pokemonName": "Espeon " },
{"pokemonName": "Slowking " },
{"pokemonName": "Misdreavus " },
{"pokemonName": "Girafarig " },
{"pokemonName": "Dunsparce " },
{"pokemonName": "Corsola " },
{"pokemonName": "Porygon2 " },
{"pokemonName": "Smoochum " },
{"pokemonName": "Celebi " },
{"pokemonName": "Ralts " },
{"pokemonName": "Kirlia " },
{"pokemonName": "Gardevoir " },
{"pokemonName": "Nosepass " },
{"pokemonName": "Sableye " },
{"pokemonName": "Meditite " },
{"pokemonName": "Medicham " },
{"pokemonName": "Spoink " },
{"pokemonName": "Grumpig " },
{"pokemonName": "Lunatone " },
{"pokemonName": "Solrock " },
{"pokemonName": "Baltoy " },
{"pokemonName": "Claydol " },
{"pokemonName": "Milotic " },
{"pokemonName": "Kecleon " },
{"pokemonName": "Shuppet " },
{"pokemonName": "Banette " },
{"pokemonName": "Chimecho " },
{"pokemonName": "Absol " },
{"pokemonName": "Latias " },
{"pokemonName": "Latios " },
{"pokemonName": "Jirachi " },
{"pokemonName": "Deoxys " },
{"pokemonName": "Deoxys-Attack " },
{"pokemonName": "Deoxys-Defense " },
{"pokemonName": "Deoxys-Speed " },
{"pokemonName": "Bastiodon " },
{"pokemonName": "Drifloon " },
{"pokemonName": "Drifblim " },
{"pokemonName": "Buneary " },
{"pokemonName": "Lopunny " },
{"pokemonName": "Mismagius " },
{"pokemonName": "Chingling " },
{"pokemonName": "Mime Jr." },
{"pokemonName": "Magnezone " },
{"pokemonName": "Togekiss " },
{"pokemonName": "Porygon-Z " },
{"pokemonName": "Gallade " },
{"pokemonName": "Probopass " },
{"pokemonName": "Uxie " },
{"pokemonName": "Mesprit " },
{"pokemonName": "Azelf " },
{"pokemonName": "Giratina-Origin " },
{"pokemonName": "Cresselia " },
{"pokemonName": "Arceus " },
{"pokemonName": "Victini " },
{"pokemonName": "Munna " },
{"pokemonName": "Musharna " },
{"pokemonName": "Woobat " },
{"pokemonName": "Swoobat " },
{"pokemonName": "Audino " },
{"pokemonName": "Sewaddle " },
{"pokemonName": "Swadloon " },
{"pokemonName": "Leavanny " },
{"pokemonName": "Sigilyph " },
{"pokemonName": "Yamask " },
{"pokemonName": "Cofagrigus " },
{"pokemonName": "Gothita " },
{"pokemonName": "Gothorita " },
{"pokemonName": "Gothitelle " },
{"pokemonName": "Solosis " },
{"pokemonName": "Duosion " },
{"pokemonName": "Reuniclus " },
{"pokemonName": "Vanillite " },
{"pokemonName": "Vanillish " },
{"pokemonName": "Vanilluxe " },
{"pokemonName": "Frillish " },
{"pokemonName": "Jellicent " },
{"pokemonName": "Alomomola " },
{"pokemonName": "Klink " },
{"pokemonName": "Klang " },
{"pokemonName": "Klinklang " },
{"pokemonName": "Elgyem " },
{"pokemonName": "Beheeyem " },
{"pokemonName": "Cryogonal " },
{"pokemonName": "Golett " },
{"pokemonName": "Golurk " },
{"pokemonName": "Meloetta " },
{"pokemonName": "Genesect " },
{"pokemonName": "Fennekin " },
{"pokemonName": "Braixen " },
{"pokemonName": "Delphox " },
{"pokemonName": "Flabébé " },
{"pokemonName": "Floette " },
{"pokemonName": "Florges " },
{"pokemonName": "Espurr " },
{"pokemonName": "Male Meowstic" },
{"pokemonName": "Female Meowstic" },
{"pokemonName": "Spritzee " },
{"pokemonName": "Aromatisse " },
{"pokemonName": "Swirlix " },
{"pokemonName": "Slurpuff " },
{"pokemonName": "Sylveon " },
{"pokemonName": "Carbink " },
{"pokemonName": "Klefki " },
{"pokemonName": "Phantump " },
{"pokemonName": "Trevenant " },
{"pokemonName": "Pumpkaboo-Small " },
{"pokemonName": "Pumpkaboo-Average " },
{"pokemonName": "Pumpkaboo-Large " },
{"pokemonName": "Pumpkaboo-Super " },
{"pokemonName": "Gourgeist-Small " },
{"pokemonName": "Gourgeist-Average " },
{"pokemonName": "Gourgeist-Large " },
{"pokemonName": "Gourgeist-Super " },
{"pokemonName": "Hoopa " }
	]
}
