{
	"name": "U-Turn",
	"note": "",
	"type":" Bug ",
	"category": "Physical",
	"pp": "20",
	"power": "70",
	"accuracy": "100",
	"summary": "Deals damage and switches the user out.",
	"viability": "U-Turn is a very good momentum shifter. It can be used when you predict your opponent to switch, getting the matchup you want. It is often used with Volt Switch, called the VoltTurn strategy",
	"pokemonByLevel": [
		{ "pokemonName": "Hoppip" },
		{ "pokemonName": "Skiploom" },
		{ "pokemonName": "Jumpluff" },
		{ "pokemonName": "Yanma" },
		{ "pokemonName": "Gligar" },
		{ "pokemonName": "Finneon" },
		{ "pokemonName": "Lumineon" },
		{ "pokemonName": "Yanmega" },
		{ "pokemonName": "Gliscor" },
		{ "pokemonName": "Archen" },
		{ "pokemonName": "Arhceops" },
		{ "pokemonName": "Zoroark" },
		{ "pokemonName": "Accelgor" },
		{ "pokemonName": "Mienfoo" },
		{ "pokemonName": "Mienshao" },
		{ "pokemonName": "Meloetta-Aria" }
	],
	"pokemonByBreeding": [
	],
	"pokemonByTM": [
	{"pokemonName": "Butterfree" },
{"pokemonName": "Beedrill" },
{"pokemonName": "Pidgey" },
{"pokemonName": "Pidgeotto" },
{"pokemonName": "Pidgeot" },
{"pokemonName": "Rattata" },
{"pokemonName": "Raticate" },
{"pokemonName": "Spearow" },
{"pokemonName": "Fearow" },
{"pokemonName": "Zubat" },
{"pokemonName": "Golbat" },
{"pokemonName": "Venomoth" },
{"pokemonName": "Meowth" },
{"pokemonName": "Persian" },
{"pokemonName": "Mankey" },
{"pokemonName": "Primeape" },
{"pokemonName": "Farfetch'd" },
{"pokemonName": "Scyther" },
{"pokemonName": "Articuno" },
{"pokemonName": "Zapdos" },
{"pokemonName": "Moltres" },
{"pokemonName": "Mew" },
{"pokemonName": "Sentret" },
{"pokemonName": "Furret" },
{"pokemonName": "Ledyba" },
{"pokemonName": "Ledian" },
{"pokemonName": "Crobat" },
{"pokemonName": "Natu" },
{"pokemonName": "Xatu" },
{"pokemonName": "Hoppip" },
{"pokemonName": "Skiploom" },
{"pokemonName": "Jumpluff" },
{"pokemonName": "Aipom" },
{"pokemonName": "Yanma" },
{"pokemonName": "Gligar" },
{"pokemonName": "Scizor" },
{"pokemonName": "Celebi" },
{"pokemonName": "Beautifly" },
{"pokemonName": "Dustox" },
{"pokemonName": "Taillow" },
{"pokemonName": "Swellow" },
{"pokemonName": "Wingull" },
{"pokemonName": "Pelipper" },
{"pokemonName": "Masquerain" },
{"pokemonName": "Ninjask" },
{"pokemonName": "Volbeat" },
{"pokemonName": "Illumise" },
{"pokemonName": "Vibrava" },
{"pokemonName": "Flygon" },
{"pokemonName": "Jirachi" },
{"pokemonName": "Chimchar" },
{"pokemonName": "Monferno" },
{"pokemonName": "Infernape" },
{"pokemonName": "Starly" },
{"pokemonName": "Staravia" },
{"pokemonName": "Staraptor" },
{"pokemonName": "Mothim" },
{"pokemonName": "Vespiquen" },
{"pokemonName": "Pachirisu" },
{"pokemonName": "Ambipom" },
{"pokemonName": "Glameow" },
{"pokemonName": "Purugly" },
{"pokemonName": "Chatot" },
{"pokemonName": "Finneon" },
{"pokemonName": "Lumineon" },
{"pokemonName": "Yanmega" },
{"pokemonName": "Gliscor" },
{"pokemonName": "Uxie" },
{"pokemonName": "Mesprit" },
{"pokemonName": "Azelf" },
{"pokemonName": "Phione" },
{"pokemonName": "Manaphy" },
{"pokemonName": "Victini" },
{"pokemonName": "Purrloin" },
{"pokemonName": "Liepard" },
{"pokemonName": "Pidove" },
{"pokemonName": "Tranquill" },
{"pokemonName": "Unfezant" },
{"pokemonName": "Woobat" },
{"pokemonName": "Swoobat" },
{"pokemonName": "Whimsicott" },
{"pokemonName": "Darumaka" },
{"pokemonName": "Darmanitan" },
{"pokemonName": "Archen" },
{"pokemonName": "Archeops" },
{"pokemonName": "Zoroark" },
{"pokemonName": "Minccino" },
{"pokemonName": "Cinccino" },
{"pokemonName": "Emolga" },
{"pokemonName": "Eelektrik" },
{"pokemonName": "Eelektross" },
{"pokemonName": "Accelgor" },
{"pokemonName": "Mienfoo" },
{"pokemonName": "Mienshao" },
{"pokemonName": "Rufflet" },
{"pokemonName": "Braviary" },
{"pokemonName": "Vullaby" },
{"pokemonName": "Mandibuzz" },
{"pokemonName": "Hydreigon" },
{"pokemonName": "Larvesta" },
{"pokemonName": "Volcarona" },
{"pokemonName": "Tornadus-Incarnate" },
{"pokemonName": "Tornadus-Therian" },
{"pokemonName": "Thundurus-Incarnate" },
{"pokemonName": "Thundurus-Therian" },
{"pokemonName": "Landorus-Incarnate" },
{"pokemonName": "Landorus-Therian" },
{"pokemonName": "Meloetta-Aria" },
{"pokemonName": "Meloetta-Pirouette" },
{"pokemonName": "Genesect" },
{"pokemonName": "Froakie" },
{"pokemonName": "Frogadier" },
{"pokemonName": "Greninja" },
{"pokemonName": "Bunnelby" },
{"pokemonName": "Diggersby" },
{"pokemonName": "Fletchling" },
{"pokemonName": "Fletchinder" },
{"pokemonName": "Talonflame" },
{"pokemonName": "Vivillon" },
{"pokemonName": "Furfrou" },
{"pokemonName": "Clauncher" },
{"pokemonName": "Clawitzer" },
{"pokemonName": "Helioptile" },
{"pokemonName": "Heliolisk" },
{"pokemonName": "Hawlucha" },
{"pokemonName": "Dedenne" },
{"pokemonName": "Noibat" },
{"pokemonName": "Noivern" },
{"pokemonName": "Yveltal" }
	],
	"pokemonByHM": [
	],
	"pokemonByTutor": [
	]
}
